core/__init__.py
core/framing.py
core/link.py
core/run_link.py
core/socket_server.py
state/__init__.py
state/action_types.py
state/actions.py
state/reducer.py
state/selectors.py
state/store.py
port_linker-1.0.7.dist-info/METADATA
port_linker-1.0.7.dist-info/WHEEL
port_linker-1.0.7.dist-info/entry_points.txt
port_linker-1.0.7.dist-info/top_level.txt
port_linker-1.0.7.dist-info/RECORD
