Metadata-Version: 2.1
Name: port-linker
Version: 1.0.7
Summary: Link serial ports and tcp sockets together
Home-page: https://github.com/JakeHillHub/port-linker
Author: Jake Hill
Author-email: jakehillgithub@gmail.net
License: UNKNOWN
Keywords: Tools
Platform: UNKNOWN
Classifier: Development Status :: 4 - Beta
Classifier: Intended Audience :: Developers
Requires-Dist: pyserial
Requires-Dist: pydux
Requires-Dist: funcy
